{
  "id": "GAD7",
  "lang": "bengali",
  "title": "GAD-7 (সাধারণ উদ্বেগ ব্যাধি প্রশ্নাবলী)",
  "instructions": "গত দুই সপ্তাহে, নিম্নলিখিত সমস্যাগুলি আপনাকে কতবার বিরক্ত করেছে?",
  "questions": [
    {
      "id": "q1",
      "text": "নার্ভাস, উদ্বিগ্ন বা অস্থির বোধ করা",
      "options": [
        { "value": 0, "label": "একেবারেই না" },
        { "value": 1, "label": "কিছু দিন" },
        { "value": 2, "label": "অর্ধেকেরও বেশি দিন" },
        { "value": 3, "label": "প্রায় প্রতিদিন" }
      ]
    },
    {
      "id": "q2",
      "text": "উদ্বেগ থামাতে না পারা বা নিয়ন্ত্রণ করতে না পারা",
      "options": [
        { "value": 0, "label": "একেবারেই না" },
        { "value": 1, "label": "কিছু দিন" },
        { "value": 2, "label": "অর্ধেকেরও বেশি দিন" },
        { "value": 3, "label": "প্রায় প্রতিদিন" }
      ]
    },
    {
      "id": "q3",
      "text": "বিভিন্ন বিষয় নিয়ে অতিরিক্ত উদ্বেগ করা",
      "options": [
        { "value": 0, "label": "একেবারেই না" },
        { "value": 1, "label": "কিছু দিন" },
        { "value": 2, "label": "অর্ধেকেরও বেশি দিন" },
        { "value": 3, "label": "প্রায় প্রতিদিন" }
      ]
    },
    {
      "id": "q4",
      "text": "বিশ্রাম নিতে অসুবিধা হওয়া",
      "options": [
        { "value": 0, "label": "একেবারেই না" },
        { "value": 1, "label": "কিছু দিন" },
        { "value": 2, "label": "অর্ধেকেরও বেশি দিন" },
        { "value": 3, "label": "প্রায় প্রতিদিন" }
      ]
    },
    {
      "id": "q5",
      "text": "এত অস্থির থাকা যে বসে থাকা কঠিন",
      "options": [
        { "value": 0, "label": "একেবারেই না" },
        { "value": 1, "label": "কিছু দিন" },
        { "value": 2, "label": "অর্ধেকেরও বেশি দিন" },
        { "value": 3, "label": "প্রায় প্রতিদিন" }
      ]
    },
    {
      "id": "q6",
      "text": "সহজেই রাগ বা বিরক্ত হওয়া",
      "options": [
        { "value": 0, "label": "একেবারেই না" },
        { "value": 1, "label": "কিছু দিন" },
        { "value": 2, "label": "অর্ধেকেরও বেশি দিন" },
        { "value": 3, "label": "প্রায় প্রতিদিন" }
      ]
    },
    {
      "id": "q7",
      "text": "মনে হওয়া যে কিছু ভয়ঙ্কর ঘটতে পারে",
      "options": [
        { "value": 0, "label": "একেবারেই না" },
        { "value": 1, "label": "কিছু দিন" },
        { "value": 2, "label": "অর্ধেকেরও বেশি দিন" },
        { "value": 3, "label": "প্রায় প্রতিদিন" }
      ]
    }
  ],
  "scoring": {
    "min": 0,
    "max": 21,
    "labels": [
      { "max": 4, "label": "ন্যূনতম উদ্বেগ" },
      { "max": 9, "label": "হালকা উদ্বেগ" },
      { "max": 14, "label": "মধ্যম উদ্বেগ" },
      { "max": 21, "label": "তীব্র উদ্বেগ" }
    ]
  }
}